autoreviewer/__init__.py
autoreviewer/__main__.py
autoreviewer/api.py
autoreviewer/cli.py
autoreviewer/py.typed
autoreviewer/review.md
autoreviewer/review.pdf
autoreviewer/utils.py
autoreviewer/version.py
autoreviewer/jcheminf/__init__.py
autoreviewer/jcheminf/__main__.py
autoreviewer/jcheminf/analysis.tsv
autoreviewer/jcheminf/doi_to_github.tsv
autoreviewer/jcheminf/jcheminf_pilot.py
autoreviewer/jcheminf/jcheminf_summary.png
autoreviewer/jcheminf/summarize.py
autoreviewer/templates/review.md
autoreviewer-0.0.5.dist-info/LICENSE
autoreviewer-0.0.5.dist-info/METADATA
autoreviewer-0.0.5.dist-info/WHEEL
autoreviewer-0.0.5.dist-info/entry_points.txt
autoreviewer-0.0.5.dist-info/top_level.txt
autoreviewer-0.0.5.dist-info/RECORD
