Metadata-Version: 2.1
Name: autoreviewer
Version: 0.0.5
Summary: Automate scientific software review
Home-page: https://github.com/cthoyt/autoreviewer
Download-URL: https://github.com/cthoyt/autoreviewer/releases
Author: Charles Tapley Hoyt
Author-email: cthoyt@gmail.com
Maintainer: Charles Tapley Hoyt
Maintainer-email: cthoyt@gmail.com
License: MIT
Project-URL: Bug Tracker, https://github.com/cthoyt/autoreviewer/issues
Project-URL: Source Code, https://github.com/cthoyt/autoreviewer
Keywords: snekpack,cookiecutter
Classifier: Development Status :: 1 - Planning
Classifier: Environment :: Console
Classifier: Intended Audience :: Developers
Classifier: License :: OSI Approved :: MIT License
Classifier: Operating System :: OS Independent
Classifier: Framework :: Pytest
Classifier: Framework :: tox
Classifier: Framework :: Sphinx
Classifier: Programming Language :: Python
Classifier: Programming Language :: Python :: 3.10
Classifier: Programming Language :: Python :: 3.11
Classifier: Programming Language :: Python :: 3.12
Classifier: Programming Language :: Python :: 3 :: Only
Requires-Python: >=3.10
License-File: LICENSE
Requires-Dist: more-itertools
Requires-Dist: tqdm
Requires-Dist: click
Requires-Dist: more-click
Requires-Dist: jinja2
Requires-Dist: ebooklib
Requires-Dist: requests
Requires-Dist: pandas
Requires-Dist: dateutils
Requires-Dist: beautifulsoup4
Requires-Dist: tabulate
Requires-Dist: pystow >=0.5.4
Requires-Dist: ratelimit
Requires-Dist: black
Requires-Dist: pyroma
Provides-Extra: docs
Requires-Dist: sphinx ; extra == 'docs'
Requires-Dist: sphinx-rtd-theme ; extra == 'docs'
Requires-Dist: sphinx-click ; extra == 'docs'
Requires-Dist: sphinx-automodapi ; extra == 'docs'
Provides-Extra: tests
Requires-Dist: pytest ; extra == 'tests'
Requires-Dist: coverage ; extra == 'tests'
